[
  {
    "summary_date": "2022-02-18",
    "period_id": 0,
    "is_longest": 1,
    "timezone": 420,
    "bedtime_end": "2022-02-19T07:21:29+07:00",
    "bedtime_start": "2022-02-18T23:10:29+07:00",
    "breath_average": 15.75,
    "duration": 29460,
    "total": 25650,
    "awake": 3810,
    "rem": 7620,
    "deep": 6810,
    "light": 11220,
    "midpoint_time": 14280,
    "efficiency": 87,
    "restless": 17,
    "onset_latency": 420,
    "hr_5min": [
      0,
      0,
      78,
      78,
      78,
      76,
      75,
      74,
      76,
      77,
      75,
      75,
      75,
      76,
      77,
      73,
      74,
      78,
      77,
      79,
      76,
      78,
      78,
      76,
      73,
      73,
      70,
      69,
      67,
      65,
      64,
      64,
      64,
      64,
      64,
      68,
      67,
      62,
      62,
      65,
      65,
      63,
      66,
      68,
      68,
      73,
      71,
      73,
      73,
      70,
      68,
      67,
      68,
      66,
      64,
      64,
      65,
      67,
      67,
      66,
      66,
      0,
      61,
      63,
      67,
      74,
      76,
      70,
      69,
      72,
      74,
      74,
      71,
      70,
      69,
      69,
      67,
      66,
      65,
      67,
      66,
      64,
      65,
      65,
      67,
      68,
      69,
      72,
      73,
      74,
      71,
      68,
      67,
      68,
      69,
      69,
      0,
      73,
      0
    ],
    "hr_average": 69.89,
    "hr_lowest": 61,
    "hypnogram_5min": "421111121111111242233333222222221111222112112333322112222212322243323333333222222222233333333334444",
    "rmssd": 31,
    "rmssd_5min": [
      0,
      0,
      25,
      27,
      30,
      33,
      29,
      36,
      30,
      29,
      32,
      25,
      24,
      22,
      22,
      41,
      33,
      16,
      26,
      16,
      22,
      16,
      13,
      17,
      21,
      21,
      33,
      41,
      46,
      42,
      34,
      26,
      27,
      26,
      49,
      33,
      36,
      54,
      41,
      25,
      31,
      59,
      41,
      30,
      32,
      14,
      23,
      19,
      19,
      30,
      38,
      41,
      32,
      52,
      41,
      36,
      28,
      24,
      25,
      44,
      37,
      0,
      79,
      39,
      40,
      17,
      15,
      40,
      50,
      31,
      17,
      20,
      28,
      20,
      19,
      19,
      39,
      31,
      31,
      27,
      62,
      33,
      28,
      45,
      29,
      31,
      29,
      49,
      25,
      13,
      34,
      30,
      37,
      25,
      19,
      47,
      0,
      31,
      0
    ],
    "score": 82,
    "score_alignment": 95,
    "score_deep": 97,
    "score_disturbances": 71,
    "score_efficiency": 88,
    "score_latency": 78,
    "score_rem": 97,
    "score_total": 75,
    "temperature_deviation": -0.26,
    "temperature_trend_deviation": -0.02,
    "bedtime_start_delta": -2971,
    "bedtime_end_delta": 26489,
    "midpoint_at_delta": 11309,
    "temperature_delta": -0.26
  }
]