[
  {
    "summary_date": "2022-07-04",
    "period_id": 1,
    "is_longest": 1,
    "timezone": -240,
    "bedtime_end": "2022-07-05T05:23:30-04:00",
    "bedtime_start": "2022-07-04T22:40:30-04:00",
    "breath_average": 15.75,
    "duration": 24180,
    "total": 20160,
    "awake": 4020,
    "rem": 4920,
    "deep": 7350,
    "light": 7890,
    "midpoint_time": 12090,
    "efficiency": 83,
    "restless": 24,
    "onset_latency": 1170,
    "hr_5min": [
      85,
      83,
      84,
      82,
      81,
      81,
      81,
      80,
      78,
      75,
      76,
      76,
      76,
      77,
      76,
      77,
      76,
      73,
      70,
      70,
      70,
      66,
      66,
      67,
      68,
      68,
      68,
      68,
      67,
      67,
      68,
      69,
      76,
      79,
      77,
      74,
      75,
      70,
      67,
      64,
      64,
      62,
      63,
      63,
      64,
      64,
      64,
      65,
      67,
      67,
      59,
      60,
      62,
      63,
      60,
      63,
      62,
      63,
      63,
      62,
      67,
      73,
      71,
      68,
      66,
      69,
      62,
      68,
      69,
      66,
      59,
      60,
      59,
      59,
      62,
      64,
      66,
      63,
      63,
      62,
      62
    ],
    "hr_average": 68.75,
    "hr_lowest": 59,
    "hypnogram_5min": "444411422211111113221222211112213333332221111111112222222212333333323222223344444",
    "rmssd": 37,
    "rmssd_5min": [
      11,
      14,
      13,
      16,
      18,
      17,
      25,
      25,
      27,
      36,
      31,
      30,
      28,
      27,
      28,
      25,
      34,
      30,
      50,
      29,
      36,
      35,
      61,
      46,
      38,
      40,
      44,
      39,
      47,
      43,
      41,
      29,
      14,
      10,
      14,
      15,
      13,
      39,
      33,
      60,
      31,
      37,
      36,
      38,
      32,
      29,
      35,
      31,
      23,
      24,
      91,
      65,
      73,
      89,
      103,
      46,
      55,
      35,
      65,
      70,
      39,
      25,
      30,
      53,
      72,
      19,
      80,
      57,
      29,
      88,
      115,
      87,
      109,
      81,
      59,
      45,
      62,
      59,
      52,
      57,
      63
    ],
    "score": 72,
    "score_alignment": 100,
    "score_deep": 98,
    "score_disturbances": 68,
    "score_efficiency": 79,
    "score_latency": 86,
    "score_rem": 69,
    "score_total": 53,
    "temperature_deviation": -0.2,
    "temperature_trend_deviation": 0.13,
    "bedtime_start_delta": -4770,
    "bedtime_end_delta": 19410,
    "midpoint_at_delta": 7320,
    "temperature_delta": -0.2
  }
]