[
  {
    "summary_date": "2022-03-28",
    "period_id": 3,
    "is_longest": 1,
    "timezone": 540,
    "bedtime_end": "2022-03-29T05:45:28+09:00",
    "bedtime_start": "2022-03-28T21:13:28+09:00",
    "breath_average": 15.625,
    "duration": 30720,
    "total": 24240,
    "awake": 6480,
    "rem": 7560,
    "deep": 6270,
    "light": 10410,
    "midpoint_time": 15930,
    "efficiency": 79,
    "restless": 24,
    "onset_latency": 1260,
    "hr_5min": [
      0,
      0,
      0,
      77,
      78,
      79,
      79,
      0,
      75,
      72,
      72,
      0,
      68,
      70,
      72,
      73,
      68,
      69,
      70,
      68,
      69,
      70,
      70,
      70,
      70,
      70,
      0,
      0,
      67,
      77,
      77,
      73,
      75,
      66,
      66,
      64,
      62,
      61,
      62,
      62,
      63,
      63,
      66,
      68,
      66,
      64,
      64,
      66,
      68,
      68,
      67,
      64,
      66,
      66,
      73,
      72,
      69,
      69,
      68,
      65,
      63,
      64,
      69,
      70,
      71,
      73,
      71,
      0,
      70,
      71,
      72,
      63,
      66,
      64,
      69,
      68,
      68,
      70,
      71,
      69,
      71,
      72,
      67,
      68,
      64,
      64,
      0,
      60,
      62,
      64,
      66,
      66,
      68,
      0,
      67,
      69,
      73,
      74,
      66,
      0,
      60,
      62,
      60
    ],
    "hr_average": 68.27,
    "hr_lowest": 60,
    "hypnogram_5min": "4444232442241112211111111124133332222212221122311112233333322222444422222222333333222322222114333343344",
    "rmssd": 40,
    "rmssd_5min": [
      0,
      0,
      0,
      16,
      18,
      19,
      33,
      0,
      27,
      31,
      38,
      0,
      47,
      33,
      33,
      38,
      57,
      44,
      32,
      47,
      39,
      32,
      31,
      35,
      31,
      28,
      0,
      0,
      53,
      14,
      13,
      19,
      17,
      69,
      55,
      70,
      83,
      74,
      71,
      97,
      76,
      82,
      54,
      58,
      46,
      39,
      43,
      32,
      30,
      31,
      29,
      58,
      36,
      64,
      20,
      24,
      28,
      28,
      55,
      49,
      68,
      46,
      35,
      25,
      30,
      22,
      28,
      0,
      26,
      23,
      27,
      73,
      51,
      64,
      32,
      42,
      36,
      28,
      29,
      51,
      29,
      26,
      73,
      28,
      58,
      56,
      0,
      99,
      52,
      37,
      29,
      31,
      30,
      0,
      44,
      27,
      15,
      30,
      49,
      0,
      80,
      65,
      89
    ],
    "score": 79,
    "score_alignment": 100,
    "score_deep": 96,
    "score_disturbances": 66,
    "score_efficiency": 69,
    "score_latency": 83,
    "score_rem": 97,
    "score_total": 70,
    "temperature_deviation": 0.3,
    "temperature_trend_deviation": 0.39,
    "bedtime_start_delta": -9992,
    "bedtime_end_delta": 20728,
    "midpoint_at_delta": 5938,
    "temperature_delta": 0.3
  }
]