[
  {
    "summary_date": "2022-10-01",
    "period_id": 0,
    "is_longest": 1,
    "timezone": 540,
    "bedtime_end": "2022-10-02T14:23:47+09:00",
    "bedtime_start": "2022-10-02T00:30:47+09:00",
    "type": "long_sleep",
    "breath_average": 16.125,
    "average_breath_variation": 4.125,
    "duration": 49980,
    "total": 39480,
    "awake": 10500,
    "rem": 13980,
    "deep": 8130,
    "light": 17370,
    "midpoint_time": 21840,
    "efficiency": 79,
    "restless": 3,
    "onset_latency": 270,
    "got_up_count": 0,
    "wake_up_count": 15,
    "hr_5min": [
      0,
      79,
      75,
      75,
      75,
      73,
      72,
      72,
      72,
      72,
      71,
      73,
      75,
      76,
      76,
      83,
      87,
      88,
      79,
      75,
      72,
      70,
      71,
      73,
      74,
      74,
      75,
      75,
      71,
      70,
      69,
      69,
      73,
      72,
      75,
      81,
      83,
      80,
      79,
      80,
      75,
      73,
      73,
      71,
      71,
      74,
      77,
      77,
      78,
      78,
      79,
      77,
      78,
      78,
      81,
      85,
      83,
      80,
      77,
      74,
      77,
      80,
      81,
      80,
      78,
      78,
      75,
      82,
      82,
      82,
      80,
      79,
      78,
      77,
      75,
      73,
      73,
      69,
      68,
      68,
      67,
      69,
      69,
      69,
      66,
      65,
      67,
      67,
      68,
      70,
      73,
      69,
      68,
      66,
      66,
      67,
      67,
      72,
      66,
      0,
      65,
      62,
      64,
      68,
      65,
      64,
      64,
      67,
      72,
      66,
      67,
      67,
      68,
      67,
      70,
      69,
      67,
      64,
      64,
      0,
      0,
      73,
      71,
      69,
      0,
      0,
      0,
      0,
      0,
      63,
      68,
      63,
      60,
      65,
      64,
      65,
      0,
      0,
      0,
      0,
      0,
      0,
      0,
      82,
      84,
      81,
      77,
      80,
      83,
      79,
      80,
      83,
      91,
      90,
      89,
      86,
      89,
      88,
      85,
      86,
      87,
      93,
      88,
      84,
      81,
      81,
      89
    ],
    "hr_average": 74.543,
    "hr_lowest": 60,
    "lowest_heart_rate_time_offset": 25290,
    "hypnogram_5min": "42211111111111133332222111112221221333233332221113333333442222333223333333222222211122322333222223222222222333222212222444224444424422224444444243333333333333334444444",
    "rmssd": 27,
    "rmssd_5min": [
      0,
      22,
      30,
      34,
      33,
      37,
      33,
      35,
      31,
      32,
      47,
      33,
      24,
      22,
      21,
      12,
      6,
      7,
      10,
      13,
      20,
      21,
      16,
      16,
      16,
      14,
      15,
      17,
      17,
      17,
      19,
      19,
      41,
      29,
      23,
      13,
      7,
      16,
      16,
      11,
      10,
      13,
      16,
      18,
      32,
      29,
      21,
      15,
      15,
      12,
      11,
      18,
      13,
      13,
      10,
      6,
      25,
      15,
      18,
      33,
      20,
      15,
      11,
      15,
      17,
      16,
      23,
      6,
      8,
      7,
      9,
      15,
      15,
      17,
      21,
      21,
      24,
      29,
      29,
      34,
      34,
      27,
      27,
      27,
      62,
      32,
      35,
      45,
      37,
      20,
      26,
      43,
      31,
      78,
      56,
      48,
      75,
      21,
      101,
      0,
      68,
      144,
      86,
      53,
      97,
      91,
      79,
      54,
      21,
      50,
      37,
      56,
      53,
      60,
      42,
      41,
      53,
      76,
      60,
      0,
      0,
      38,
      34,
      41,
      0,
      0,
      0,
      0,
      0,
      83,
      55,
      101,
      125,
      94,
      79,
      116,
      0,
      0,
      0,
      0,
      0,
      0,
      0,
      15,
      20,
      19,
      27,
      33,
      20,
      24,
      27,
      16,
      11,
      16,
      15,
      11,
      11,
      11,
      18,
      14,
      22,
      13,
      13,
      14,
      15,
      16,
      15
    ],
    "score": 81,
    "score_alignment": 13,
    "score_deep": 99,
    "score_disturbances": 71,
    "score_efficiency": 69,
    "score_latency": 72,
    "score_rem": 100,
    "score_total": 100,
    "temperature_deviation": 0.03,
    "temperature_trend_deviation": 0.06,
    "bedtime_start_delta": 1847,
    "bedtime_end_delta": 51827,
    "midpoint_at_delta": 23687,
    "temperature_delta": 0.03
  }
]