[
  {
    "summary_date": "2021-11-19",
    "period_id": 0,
    "is_longest": 1,
    "timezone": -300,
    "bedtime_end": "2021-11-20T09:45:31-05:00",
    "bedtime_start": "2021-11-19T20:57:31-05:00",
    "breath_average": 15.875,
    "duration": 46080,
    "total": 23820,
    "awake": 22260,
    "rem": 5730,
    "deep": 2730,
    "light": 15360,
    "midpoint_time": 30750,
    "efficiency": 52,
    "restless": 32,
    "onset_latency": 4140,
    "hr_5min": [
      0,
      95,
      92,
      92,
      90,
      88,
      88,
      89,
      88,
      89,
      86,
      84,
      88,
      87,
      87,
      87,
      0,
      0,
      94,
      95,
      0,
      0,
      0,
      0,
      0,
      0,
      0,
      0,
      0,
      0,
      0,
      0,
      0,
      0,
      0,
      0,
      82,
      82,
      0,
      81,
      82,
      0,
      0,
      0,
      0,
      0,
      0,
      0,
      0,
      0,
      0,
      0,
      0,
      0,
      0,
      0,
      0,
      0,
      0,
      0,
      0,
      0,
      0,
      92,
      90,
      91,
      91,
      0,
      0,
      0,
      87,
      82,
      82,
      79,
      78,
      77,
      76,
      75,
      74,
      76,
      78,
      77,
      82,
      82,
      83,
      80,
      78,
      75,
      74,
      74,
      76,
      75,
      73,
      74,
      74,
      74,
      71,
      66,
      66,
      68,
      69,
      67,
      66,
      67,
      68,
      67,
      69,
      76,
      72,
      71,
      70,
      69,
      70,
      69,
      68,
      74,
      67,
      65,
      65,
      65,
      64,
      64,
      65,
      64,
      65,
      67,
      69,
      65,
      67,
      65,
      66,
      66,
      69,
      66,
      0,
      0,
      0,
      67,
      67,
      66,
      68,
      68,
      74,
      75,
      67,
      68,
      68,
      69,
      67,
      67,
      68,
      66,
      67,
      0
    ],
    "hypnogram_5min": "4244442444424421444444444444444444444444244444444444444444444444442444222222222224333222222211122222222211133333324322233333312222222244422223333222222244",
    "rmssd": 44,
    "rmssd_5min": [
      0,
      10,
      14,
      14,
      14,
      17,
      17,
      17,
      15,
      16,
      19,
      17,
      23,
      18,
      14,
      14,
      0,
      0,
      17,
      10,
      0,
      0,
      0,
      0,
      0,
      0,
      0,
      0,
      0,
      0,
      0,
      0,
      0,
      0,
      0,
      0,
      23,
      27,
      0,
      57,
      19,
      0,
      0,
      0,
      0,
      0,
      0,
      0,
      0,
      0,
      0,
      0,
      0,
      0,
      0,
      0,
      0,
      0,
      0,
      0,
      0,
      0,
      0,
      19,
      15,
      13,
      11,
      0,
      0,
      0,
      17,
      19,
      21,
      32,
      28,
      29,
      33,
      34,
      37,
      30,
      33,
      36,
      12,
      18,
      19,
      30,
      25,
      41,
      45,
      40,
      29,
      34,
      38,
      33,
      34,
      46,
      62,
      80,
      86,
      55,
      55,
      71,
      66,
      57,
      57,
      54,
      54,
      30,
      28,
      30,
      29,
      42,
      35,
      66,
      69,
      30,
      42,
      48,
      54,
      50,
      47,
      51,
      47,
      57,
      50,
      39,
      58,
      81,
      53,
      89,
      84,
      63,
      87,
      81,
      0,
      0,
      0,
      45,
      42,
      52,
      47,
      58,
      34,
      29,
      46,
      45,
      43,
      49,
      88,
      72,
      98,
      72,
      69,
      0
    ],
    "score": 51,
    "score_alignment": 24,
    "score_deep": 47,
    "score_disturbances": 66,
    "score_efficiency": 18,
    "score_latency": 4,
    "score_rem": 80,
    "score_total": 68,
    "temperature_deviation": 0.09,
    "temperature_trend_deviation": 0.23,
    "bedtime_start_delta": -10949,
    "bedtime_end_delta": 35131,
    "midpoint_at_delta": 19801,
    "temperature_delta": 0.09,
    "hr_lowest": 64,
    "hr_average": 75.09
  }
]