{
  "2021-12-26": {
    "steps": 6141,
    "total": 274,
    "cal_active": 352,
    "cal_total": 2773,
    "score": 82
  },
  "2021-12-27": {
    "steps": 5672,
    "total": 175,
    "cal_active": 288,
    "cal_total": 2672,
    "score": 88
  },
  "2021-12-28": {
    "steps": 10274,
    "total": 309,
    "cal_active": 511,
    "cal_total": 2997,
    "score": 87
  },
  "2021-12-29": {
    "steps": 10076,
    "total": 282,
    "cal_active": 501,
    "cal_total": 2949,
    "score": 87
  },
  "2021-12-30": {
    "steps": 7155,
    "total": 220,
    "cal_active": 379,
    "cal_total": 2726,
    "score": 82
  }
}