[
  {
    "summary_date": "2021-12-29",
    "period_id": 1,
    "is_longest": 1,
    "timezone": 420,
    "bedtime_end": "2021-12-30T08:49:32+07:00",
    "bedtime_start": "2021-12-29T23:43:32+07:00",
    "breath_average": 16,
    "duration": 32760,
    "total": 27450,
    "awake": 5310,
    "rem": 8520,
    "deep": 5910,
    "light": 13020,
    "midpoint_time": 16680,
    "efficiency": 84,
    "restless": 22,
    "onset_latency": 1020,
    "hr_5min": [
      0,
      0,
      91,
      89,
      88,
      87,
      86,
      83,
      82,
      82,
      82,
      83,
      82,
      81,
      80,
      80,
      81,
      82,
      82,
      85,
      0,
      0,
      81,
      79,
      79,
      79,
      77,
      73,
      74,
      75,
      75,
      77,
      76,
      74,
      73,
      0,
      68,
      69,
      0,
      0,
      69,
      69,
      71,
      72,
      73,
      73,
      74,
      74,
      75,
      74,
      74,
      77,
      77,
      77,
      73,
      74,
      75,
      75,
      0,
      69,
      67,
      68,
      67,
      64,
      64,
      69,
      68,
      68,
      69,
      69,
      69,
      70,
      70,
      70,
      70,
      71,
      72,
      0,
      72,
      72,
      72,
      75,
      72,
      70,
      0,
      68,
      65,
      67,
      67,
      66,
      66,
      67,
      68,
      68,
      70,
      72,
      71,
      73,
      0,
      71,
      70,
      71,
      71,
      72,
      69,
      69,
      69,
      70,
      72,
      77
    ],
    "hr_average": 73.71,
    "hr_lowest": 64,
    "hypnogram_5min": "44433344221111221113333332221222224411331111111111433343344222222222224222223332333332222222223333333222232444",
    "rmssd": 26,
    "rmssd_5min": [
      0,
      0,
      15,
      10,
      10,
      10,
      12,
      16,
      17,
      16,
      17,
      16,
      18,
      19,
      20,
      17,
      17,
      19,
      19,
      11,
      0,
      0,
      15,
      15,
      14,
      14,
      30,
      23,
      19,
      23,
      19,
      18,
      21,
      28,
      33,
      0,
      48,
      31,
      0,
      0,
      42,
      35,
      31,
      32,
      30,
      36,
      32,
      32,
      30,
      33,
      38,
      17,
      15,
      18,
      30,
      27,
      19,
      18,
      0,
      30,
      35,
      30,
      35,
      52,
      45,
      42,
      36,
      31,
      39,
      28,
      63,
      29,
      26,
      27,
      51,
      45,
      23,
      0,
      30,
      31,
      22,
      15,
      27,
      21,
      0,
      59,
      48,
      35,
      43,
      36,
      28,
      28,
      27,
      44,
      31,
      28,
      21,
      20,
      0,
      26,
      40,
      31,
      30,
      34,
      27,
      20,
      49,
      46,
      39,
      34
    ],
    "score": 81,
    "score_alignment": 58,
    "score_deep": 96,
    "score_disturbances": 66,
    "score_efficiency": 81,
    "score_latency": 94,
    "score_rem": 99,
    "score_total": 82,
    "temperature_deviation": -0.33,
    "temperature_trend_deviation": 0.32,
    "bedtime_start_delta": -988,
    "bedtime_end_delta": 31772,
    "midpoint_at_delta": 15692,
    "temperature_delta": -0.33
  }
]